{
  "$schema": "https://mintlify.com/docs.json",
  "theme": "maple",
  "name": "Cronozen Docs",
  "description": "Developer documentation for the Cronozen multi-tenant SaaS platform",
  "colors": {
    "primary": "#D97B57",
    "light": "#FAF9F7",
    "dark": "#C06A48"
  },
  "logo": {
    "light": "/images/logo-light.svg",
    "dark": "/images/logo-dark.svg",
    "href": "https://cronozen.com"
  },
  "favicon": "/images/favicon.svg",
  "navigation": {
    "groups": [
      {
        "group": "Getting Started",
        "pages": [
          "introduction",
          "getting-started/quickstart",
          "getting-started/concepts"
        ]
      },
      {
        "group": "Architecture",
        "pages": [
          "architecture/overview",
          "architecture/multi-tenant",
          "architecture/dpu",
          "architecture/proof-pipeline"
        ]
      },
      {
        "group": "Authentication",
        "pages": [
          "auth/overview",
          "auth/jwt",
          "auth/multi-tenant-auth"
        ]
      },
      {
        "group": "Tenant System",
        "pages": [
          "tenant/overview",
          "tenant/workspace",
          "tenant/membership"
        ]
      },
      {
        "group": "AI Agents",
        "pages": [
          "agents/overview",
          "agents/workflow"
        ]
      },
      {
        "group": "Guides",
        "pages": [
          "guides/white-label-setup",
          "guides/lms-integration"
        ]
      },
      {
        "group": "API Reference",
        "pages": [
          "api-reference/overview",
          "api-reference/authentication",
          "api-reference/tenants",
          "api-reference/workflows"
        ]
      }
    ]
  },
  "topbar": {
    "links": [
      {
        "name": "Platform",
        "url": "https://cronozen.com"
      }
    ],
    "cta": {
      "name": "Get Started",
      "url": "https://cronozen.com/auth"
    }
  },
  "footerSocials": {
    "website": "https://cronozen.com",
    "github": "https://github.com/devatthearound"
  }
}
